sapply/__init__.py
sapply/charmap.py
sapply/cli.py
sapply/cmapdefs.py
sapply/flip.py
sapply/morse.py
sapply/tokens.py
sapply/zalgo.py
sapply/resources/__init__.py
sapply/resources/bold-italic-sans.json
sapply/resources/bold-italic.json
sapply/resources/bold-sans.json
sapply/resources/bold.json
sapply/resources/doublestruck.json
sapply/resources/italic-sans.json
sapply/resources/italic.json
sapply/resources/med.json
sapply/resources/monospace.json
sapply/resources/old-eng.json
sapply/resources/subscripts.json
sapply/resources/superscripts.json
sapply-0.1.14.dist-info/LICENSE
sapply-0.1.14.dist-info/METADATA
sapply-0.1.14.dist-info/WHEEL
sapply-0.1.14.dist-info/entry_points.txt
sapply-0.1.14.dist-info/top_level.txt
sapply-0.1.14.dist-info/RECORD
