Metadata-Version: 2.1
Name: sapply
Version: 0.1.14
Summary: Easily apply arbitrary string manipulations on text.
Home-page: https://github.com/jmdaemon/sapply
Author: Joseph Diza
Author-email: josephm.diza@gmail.com
License: MIT
Project-URL: Bug Tracker, https://github.com/jmdaemon/sapply/issues
Classifier: Programming Language :: Python :: 3
Classifier: License :: OSI Approved :: MIT License
Classifier: Operating System :: OS Independent
Requires-Python: >=3.6
License-File: LICENSE
Requires-Dist: wora
Requires-Dist: spacy
Requires-Dist: regex
